flatdict.py
flatdict-3.4.0.dist-info/LICENSE
flatdict-3.4.0.dist-info/METADATA
flatdict-3.4.0.dist-info/WHEEL
flatdict-3.4.0.dist-info/top_level.txt
flatdict-3.4.0.dist-info/zip-safe
flatdict-3.4.0.dist-info/RECORD
